{
  "ABIRoot": {
    "kind": "Root",
    "name": "FintechSDKRedirectScenario",
    "printedName": "FintechSDKRedirectScenario",
    "children": [
      {
        "kind": "Import",
        "name": "Foundation",
        "printedName": "Foundation",
        "declKind": "Import",
        "moduleName": "FintechSDKRedirectScenario"
      },
      {
        "kind": "Import",
        "name": "FintechSDKAnalyticsInterfaces",
        "printedName": "FintechSDKAnalyticsInterfaces",
        "declKind": "Import",
        "moduleName": "FintechSDKRedirectScenario"
      },
      {
        "kind": "Import",
        "name": "FintechSDKNetworkInterfaces",
        "printedName": "FintechSDKNetworkInterfaces",
        "declKind": "Import",
        "moduleName": "FintechSDKRedirectScenario"
      },
      {
        "kind": "Import",
        "name": "Foundation",
        "printedName": "Foundation",
        "declKind": "Import",
        "moduleName": "FintechSDKRedirectScenario"
      },
      {
        "kind": "Import",
        "name": "UIKit",
        "printedName": "UIKit",
        "declKind": "Import",
        "moduleName": "FintechSDKRedirectScenario"
      },
      {
        "kind": "Import",
        "name": "SwiftUI",
        "printedName": "SwiftUI",
        "declKind": "Import",
        "moduleName": "FintechSDKRedirectScenario"
      },
      {
        "kind": "Import",
        "name": "FintechSDKLoaderScreen",
        "printedName": "FintechSDKLoaderScreen",
        "declKind": "Import",
        "moduleName": "FintechSDKRedirectScenario",
        "declAttributes": [
          "SPIAccessControl"
        ]
      },
      {
        "kind": "TypeDecl",
        "name": "FTPollingStatus",
        "printedName": "FTPollingStatus",
        "children": [
          {
            "kind": "Var",
            "name": "success",
            "printedName": "success",
            "children": [
              {
                "kind": "TypeFunc",
                "name": "Function",
                "printedName": "(FintechSDKRedirectScenario.FTPollingStatus.Type) -> FintechSDKRedirectScenario.FTPollingStatus",
                "children": [
                  {
                    "kind": "TypeNominal",
                    "name": "FTPollingStatus",
                    "printedName": "FintechSDKRedirectScenario.FTPollingStatus",
                    "usr": "s:26FintechSDKRedirectScenario15FTPollingStatusO"
                  },
                  {
                    "kind": "TypeNominal",
                    "name": "Metatype",
                    "printedName": "FintechSDKRedirectScenario.FTPollingStatus.Type",
                    "children": [
                      {
                        "kind": "TypeNominal",
                        "name": "FTPollingStatus",
                        "printedName": "FintechSDKRedirectScenario.FTPollingStatus",
                        "usr": "s:26FintechSDKRedirectScenario15FTPollingStatusO"
                      }
                    ]
                  }
                ]
              }
            ],
            "declKind": "EnumElement",
            "usr": "s:26FintechSDKRedirectScenario15FTPollingStatusO7successyA2CmF",
            "mangledName": "$s26FintechSDKRedirectScenario15FTPollingStatusO7successyA2CmF",
            "moduleName": "FintechSDKRedirectScenario"
          },
          {
            "kind": "Var",
            "name": "error",
            "printedName": "error",
            "children": [
              {
                "kind": "TypeFunc",
                "name": "Function",
                "printedName": "(FintechSDKRedirectScenario.FTPollingStatus.Type) -> FintechSDKRedirectScenario.FTPollingStatus",
                "children": [
                  {
                    "kind": "TypeNominal",
                    "name": "FTPollingStatus",
                    "printedName": "FintechSDKRedirectScenario.FTPollingStatus",
                    "usr": "s:26FintechSDKRedirectScenario15FTPollingStatusO"
                  },
                  {
                    "kind": "TypeNominal",
                    "name": "Metatype",
                    "printedName": "FintechSDKRedirectScenario.FTPollingStatus.Type",
                    "children": [
                      {
                        "kind": "TypeNominal",
                        "name": "FTPollingStatus",
                        "printedName": "FintechSDKRedirectScenario.FTPollingStatus",
                        "usr": "s:26FintechSDKRedirectScenario15FTPollingStatusO"
                      }
                    ]
                  }
                ]
              }
            ],
            "declKind": "EnumElement",
            "usr": "s:26FintechSDKRedirectScenario15FTPollingStatusO5erroryA2CmF",
            "mangledName": "$s26FintechSDKRedirectScenario15FTPollingStatusO5erroryA2CmF",
            "moduleName": "FintechSDKRedirectScenario"
          },
          {
            "kind": "Var",
            "name": "cancel",
            "printedName": "cancel",
            "children": [
              {
                "kind": "TypeFunc",
                "name": "Function",
                "printedName": "(FintechSDKRedirectScenario.FTPollingStatus.Type) -> FintechSDKRedirectScenario.FTPollingStatus",
                "children": [
                  {
                    "kind": "TypeNominal",
                    "name": "FTPollingStatus",
                    "printedName": "FintechSDKRedirectScenario.FTPollingStatus",
                    "usr": "s:26FintechSDKRedirectScenario15FTPollingStatusO"
                  },
                  {
                    "kind": "TypeNominal",
                    "name": "Metatype",
                    "printedName": "FintechSDKRedirectScenario.FTPollingStatus.Type",
                    "children": [
                      {
                        "kind": "TypeNominal",
                        "name": "FTPollingStatus",
                        "printedName": "FintechSDKRedirectScenario.FTPollingStatus",
                        "usr": "s:26FintechSDKRedirectScenario15FTPollingStatusO"
                      }
                    ]
                  }
                ]
              }
            ],
            "declKind": "EnumElement",
            "usr": "s:26FintechSDKRedirectScenario15FTPollingStatusO6cancelyA2CmF",
            "mangledName": "$s26FintechSDKRedirectScenario15FTPollingStatusO6cancelyA2CmF",
            "moduleName": "FintechSDKRedirectScenario"
          },
          {
            "kind": "Constructor",
            "name": "init",
            "printedName": "init(rawValue:)",
            "children": [
              {
                "kind": "TypeNominal",
                "name": "Optional",
                "printedName": "FintechSDKRedirectScenario.FTPollingStatus?",
                "children": [
                  {
                    "kind": "TypeNominal",
                    "name": "FTPollingStatus",
                    "printedName": "FintechSDKRedirectScenario.FTPollingStatus",
                    "usr": "s:26FintechSDKRedirectScenario15FTPollingStatusO"
                  }
                ],
                "usr": "s:Sq"
              },
              {
                "kind": "TypeNominal",
                "name": "String",
                "printedName": "Swift.String",
                "usr": "s:SS"
              }
            ],
            "declKind": "Constructor",
            "usr": "s:26FintechSDKRedirectScenario15FTPollingStatusO8rawValueACSgSS_tcfc",
            "mangledName": "$s26FintechSDKRedirectScenario15FTPollingStatusO8rawValueACSgSS_tcfc",
            "moduleName": "FintechSDKRedirectScenario",
            "implicit": true,
            "init_kind": "Designated"
          },
          {
            "kind": "Var",
            "name": "rawValue",
            "printedName": "rawValue",
            "children": [
              {
                "kind": "TypeNominal",
                "name": "String",
                "printedName": "Swift.String",
                "usr": "s:SS"
              }
            ],
            "declKind": "Var",
            "usr": "s:26FintechSDKRedirectScenario15FTPollingStatusO8rawValueSSvp",
            "mangledName": "$s26FintechSDKRedirectScenario15FTPollingStatusO8rawValueSSvp",
            "moduleName": "FintechSDKRedirectScenario",
            "implicit": true,
            "accessors": [
              {
                "kind": "Accessor",
                "name": "Get",
                "printedName": "Get()",
                "children": [
                  {
                    "kind": "TypeNominal",
                    "name": "String",
                    "printedName": "Swift.String",
                    "usr": "s:SS"
                  }
                ],
                "declKind": "Accessor",
                "usr": "s:26FintechSDKRedirectScenario15FTPollingStatusO8rawValueSSvg",
                "mangledName": "$s26FintechSDKRedirectScenario15FTPollingStatusO8rawValueSSvg",
                "moduleName": "FintechSDKRedirectScenario",
                "implicit": true,
                "accessorKind": "get"
              }
            ]
          }
        ],
        "declKind": "Enum",
        "usr": "s:26FintechSDKRedirectScenario15FTPollingStatusO",
        "mangledName": "$s26FintechSDKRedirectScenario15FTPollingStatusO",
        "moduleName": "FintechSDKRedirectScenario",
        "declAttributes": [
          "AccessControl"
        ],
        "enumRawTypeName": "String",
        "conformances": [
          {
            "kind": "Conformance",
            "name": "Copyable",
            "printedName": "Copyable",
            "usr": "s:s8CopyableP",
            "mangledName": "$ss8CopyableP"
          },
          {
            "kind": "Conformance",
            "name": "Escapable",
            "printedName": "Escapable",
            "usr": "s:s9EscapableP",
            "mangledName": "$ss9EscapableP"
          },
          {
            "kind": "Conformance",
            "name": "Equatable",
            "printedName": "Equatable",
            "usr": "s:SQ",
            "mangledName": "$sSQ"
          },
          {
            "kind": "Conformance",
            "name": "Hashable",
            "printedName": "Hashable",
            "usr": "s:SH",
            "mangledName": "$sSH"
          },
          {
            "kind": "Conformance",
            "name": "RawRepresentable",
            "printedName": "RawRepresentable",
            "children": [
              {
                "kind": "TypeWitness",
                "name": "RawValue",
                "printedName": "RawValue",
                "children": [
                  {
                    "kind": "TypeNominal",
                    "name": "String",
                    "printedName": "Swift.String",
                    "usr": "s:SS"
                  }
                ]
              }
            ],
            "usr": "s:SY",
            "mangledName": "$sSY"
          }
        ]
      },
      {
        "kind": "TypeDecl",
        "name": "FTPollingScenario",
        "printedName": "FTPollingScenario",
        "children": [
          {
            "kind": "Function",
            "name": "run",
            "printedName": "run(paymentURL:with:animated:)",
            "children": [
              {
                "kind": "TypeNominal",
                "name": "FTPollingStatus",
                "printedName": "FintechSDKRedirectScenario.FTPollingStatus",
                "usr": "s:26FintechSDKRedirectScenario15FTPollingStatusO"
              },
              {
                "kind": "TypeNominal",
                "name": "URL",
                "printedName": "Foundation.URL",
                "usr": "s:10Foundation3URLV"
              },
              {
                "kind": "TypeNominal",
                "name": "UIViewController",
                "printedName": "UIKit.UIViewController",
                "usr": "c:objc(cs)UIViewController"
              },
              {
                "kind": "TypeNominal",
                "name": "Bool",
                "printedName": "Swift.Bool",
                "usr": "s:Sb"
              }
            ],
            "declKind": "Func",
            "usr": "s:26FintechSDKRedirectScenario09FTPollingC0P3run10paymentURL4with8animatedAA0D6StatusO10Foundation0G0V_So16UIViewControllerCSbtYaF",
            "mangledName": "$s26FintechSDKRedirectScenario09FTPollingC0P3run10paymentURL4with8animatedAA0D6StatusO10Foundation0G0V_So16UIViewControllerCSbtYaF",
            "moduleName": "FintechSDKRedirectScenario",
            "genericSig": "<τ_0_0 where τ_0_0 : FintechSDKRedirectScenario.FTPollingScenario>",
            "sugared_genericSig": "<Self where Self : FintechSDKRedirectScenario.FTPollingScenario>",
            "protocolReq": true,
            "declAttributes": [
              "Custom",
              "DiscardableResult"
            ],
            "reqNewWitnessTableEntry": true,
            "funcSelfKind": "NonMutating"
          },
          {
            "kind": "Function",
            "name": "handleURL",
            "printedName": "handleURL(_:)",
            "children": [
              {
                "kind": "TypeNominal",
                "name": "Bool",
                "printedName": "Swift.Bool",
                "usr": "s:Sb"
              },
              {
                "kind": "TypeNominal",
                "name": "URL",
                "printedName": "Foundation.URL",
                "usr": "s:10Foundation3URLV"
              }
            ],
            "declKind": "Func",
            "usr": "s:26FintechSDKRedirectScenario09FTPollingC0P9handleURLySb10Foundation0F0VF",
            "mangledName": "$s26FintechSDKRedirectScenario09FTPollingC0P9handleURLySb10Foundation0F0VF",
            "moduleName": "FintechSDKRedirectScenario",
            "genericSig": "<τ_0_0 where τ_0_0 : FintechSDKRedirectScenario.FTPollingScenario>",
            "sugared_genericSig": "<Self where Self : FintechSDKRedirectScenario.FTPollingScenario>",
            "protocolReq": true,
            "reqNewWitnessTableEntry": true,
            "funcSelfKind": "NonMutating"
          },
          {
            "kind": "Function",
            "name": "handleUserActivity",
            "printedName": "handleUserActivity(_:)",
            "children": [
              {
                "kind": "TypeNominal",
                "name": "Bool",
                "printedName": "Swift.Bool",
                "usr": "s:Sb"
              },
              {
                "kind": "TypeNominal",
                "name": "NSUserActivity",
                "printedName": "Foundation.NSUserActivity",
                "usr": "c:objc(cs)NSUserActivity"
              }
            ],
            "declKind": "Func",
            "usr": "s:26FintechSDKRedirectScenario09FTPollingC0P18handleUserActivityySbSo06NSUserG0CF",
            "mangledName": "$s26FintechSDKRedirectScenario09FTPollingC0P18handleUserActivityySbSo06NSUserG0CF",
            "moduleName": "FintechSDKRedirectScenario",
            "genericSig": "<τ_0_0 where τ_0_0 : FintechSDKRedirectScenario.FTPollingScenario>",
            "sugared_genericSig": "<Self where Self : FintechSDKRedirectScenario.FTPollingScenario>",
            "protocolReq": true,
            "reqNewWitnessTableEntry": true,
            "funcSelfKind": "NonMutating"
          }
        ],
        "declKind": "Protocol",
        "usr": "s:26FintechSDKRedirectScenario09FTPollingC0P",
        "mangledName": "$s26FintechSDKRedirectScenario09FTPollingC0P",
        "moduleName": "FintechSDKRedirectScenario",
        "declAttributes": [
          "AccessControl"
        ],
        "conformances": [
          {
            "kind": "Conformance",
            "name": "Escapable",
            "printedName": "Escapable",
            "usr": "s:s9EscapableP",
            "mangledName": "$ss9EscapableP"
          },
          {
            "kind": "Conformance",
            "name": "Copyable",
            "printedName": "Copyable",
            "usr": "s:s8CopyableP",
            "mangledName": "$ss8CopyableP"
          }
        ]
      },
      {
        "kind": "TypeDecl",
        "name": "FTPollingScenarioImpl",
        "printedName": "FTPollingScenarioImpl",
        "children": [
          {
            "kind": "Constructor",
            "name": "init",
            "printedName": "init(clientId:paybackendNetworkClient:redirectScenario:eventReporter:errorReporter:)",
            "children": [
              {
                "kind": "TypeNominal",
                "name": "FTPollingScenarioImpl",
                "printedName": "FintechSDKRedirectScenario.FTPollingScenarioImpl",
                "usr": "s:26FintechSDKRedirectScenario09FTPollingC4ImplC"
              },
              {
                "kind": "TypeNominal",
                "name": "Optional",
                "printedName": "Swift.String?",
                "children": [
                  {
                    "kind": "TypeNominal",
                    "name": "String",
                    "printedName": "Swift.String",
                    "usr": "s:SS"
                  }
                ],
                "usr": "s:Sq"
              },
              {
                "kind": "TypeNominal",
                "name": "FintechNetworkClient",
                "printedName": "any FintechSDKNetworkInterfaces.FintechNetworkClient",
                "usr": "s:27FintechSDKNetworkInterfaces0A13NetworkClientP"
              },
              {
                "kind": "TypeNominal",
                "name": "FTRedirectScenario",
                "printedName": "any FintechSDKRedirectScenario.FTRedirectScenario",
                "usr": "s:26FintechSDKRedirectScenario010FTRedirectC0P"
              },
              {
                "kind": "TypeNominal",
                "name": "FintechAnalyticsEventReporter",
                "printedName": "any FintechSDKAnalyticsInterfaces.FintechAnalyticsEventReporter",
                "usr": "s:29FintechSDKAnalyticsInterfaces0A22AnalyticsEventReporterP"
              },
              {
                "kind": "TypeNominal",
                "name": "FintechAnalyticsErrorReporter",
                "printedName": "any FintechSDKAnalyticsInterfaces.FintechAnalyticsErrorReporter",
                "usr": "s:29FintechSDKAnalyticsInterfaces0A22AnalyticsErrorReporterP"
              }
            ],
            "declKind": "Constructor",
            "usr": "s:26FintechSDKRedirectScenario09FTPollingC4ImplC8clientId23paybackendNetworkClient08redirectC013eventReporter05errorM0ACSSSg_0A20SDKNetworkInterfaces0aiJ0_pAA010FTRedirectC0_p0a12SDKAnalyticsP00a14AnalyticsEventM0_pAM0as5ErrorM0_ptcfc",
            "mangledName": "$s26FintechSDKRedirectScenario09FTPollingC4ImplC8clientId23paybackendNetworkClient08redirectC013eventReporter05errorM0ACSSSg_0A20SDKNetworkInterfaces0aiJ0_pAA010FTRedirectC0_p0a12SDKAnalyticsP00a14AnalyticsEventM0_pAM0as5ErrorM0_ptcfc",
            "moduleName": "FintechSDKRedirectScenario",
            "declAttributes": [
              "AccessControl"
            ],
            "init_kind": "Designated"
          },
          {
            "kind": "Function",
            "name": "run",
            "printedName": "run(paymentURL:with:animated:)",
            "children": [
              {
                "kind": "TypeNominal",
                "name": "FTPollingStatus",
                "printedName": "FintechSDKRedirectScenario.FTPollingStatus",
                "usr": "s:26FintechSDKRedirectScenario15FTPollingStatusO"
              },
              {
                "kind": "TypeNominal",
                "name": "URL",
                "printedName": "Foundation.URL",
                "usr": "s:10Foundation3URLV"
              },
              {
                "kind": "TypeNominal",
                "name": "UIViewController",
                "printedName": "UIKit.UIViewController",
                "usr": "c:objc(cs)UIViewController"
              },
              {
                "kind": "TypeNominal",
                "name": "Bool",
                "printedName": "Swift.Bool",
                "usr": "s:Sb"
              }
            ],
            "declKind": "Func",
            "usr": "s:26FintechSDKRedirectScenario09FTPollingC4ImplC3run10paymentURL4with8animatedAA0D6StatusO10Foundation0H0V_So16UIViewControllerCSbtYaF",
            "mangledName": "$s26FintechSDKRedirectScenario09FTPollingC4ImplC3run10paymentURL4with8animatedAA0D6StatusO10Foundation0H0V_So16UIViewControllerCSbtYaF",
            "moduleName": "FintechSDKRedirectScenario",
            "declAttributes": [
              "Final",
              "AccessControl",
              "Custom"
            ],
            "funcSelfKind": "NonMutating"
          },
          {
            "kind": "Function",
            "name": "handleURL",
            "printedName": "handleURL(_:)",
            "children": [
              {
                "kind": "TypeNominal",
                "name": "Bool",
                "printedName": "Swift.Bool",
                "usr": "s:Sb"
              },
              {
                "kind": "TypeNominal",
                "name": "URL",
                "printedName": "Foundation.URL",
                "usr": "s:10Foundation3URLV"
              }
            ],
            "declKind": "Func",
            "usr": "s:26FintechSDKRedirectScenario09FTPollingC4ImplC9handleURLySb10Foundation0G0VF",
            "mangledName": "$s26FintechSDKRedirectScenario09FTPollingC4ImplC9handleURLySb10Foundation0G0VF",
            "moduleName": "FintechSDKRedirectScenario",
            "declAttributes": [
              "Final",
              "AccessControl"
            ],
            "isFromExtension": true,
            "funcSelfKind": "NonMutating"
          },
          {
            "kind": "Function",
            "name": "handleUserActivity",
            "printedName": "handleUserActivity(_:)",
            "children": [
              {
                "kind": "TypeNominal",
                "name": "Bool",
                "printedName": "Swift.Bool",
                "usr": "s:Sb"
              },
              {
                "kind": "TypeNominal",
                "name": "NSUserActivity",
                "printedName": "Foundation.NSUserActivity",
                "usr": "c:objc(cs)NSUserActivity"
              }
            ],
            "declKind": "Func",
            "usr": "s:26FintechSDKRedirectScenario09FTPollingC4ImplC18handleUserActivityySbSo06NSUserH0CF",
            "mangledName": "$s26FintechSDKRedirectScenario09FTPollingC4ImplC18handleUserActivityySbSo06NSUserH0CF",
            "moduleName": "FintechSDKRedirectScenario",
            "declAttributes": [
              "Final",
              "AccessControl"
            ],
            "isFromExtension": true,
            "funcSelfKind": "NonMutating"
          }
        ],
        "declKind": "Class",
        "usr": "s:26FintechSDKRedirectScenario09FTPollingC4ImplC",
        "mangledName": "$s26FintechSDKRedirectScenario09FTPollingC4ImplC",
        "moduleName": "FintechSDKRedirectScenario",
        "declAttributes": [
          "Final",
          "AccessControl"
        ],
        "conformances": [
          {
            "kind": "Conformance",
            "name": "Copyable",
            "printedName": "Copyable",
            "usr": "s:s8CopyableP",
            "mangledName": "$ss8CopyableP"
          },
          {
            "kind": "Conformance",
            "name": "Escapable",
            "printedName": "Escapable",
            "usr": "s:s9EscapableP",
            "mangledName": "$ss9EscapableP"
          },
          {
            "kind": "Conformance",
            "name": "FTPollingScenario",
            "printedName": "FTPollingScenario",
            "usr": "s:26FintechSDKRedirectScenario09FTPollingC0P",
            "mangledName": "$s26FintechSDKRedirectScenario09FTPollingC0P"
          }
        ]
      },
      {
        "kind": "Import",
        "name": "Foundation",
        "printedName": "Foundation",
        "declKind": "Import",
        "moduleName": "FintechSDKRedirectScenario"
      },
      {
        "kind": "Import",
        "name": "FintechSDKNetworkInterfaces",
        "printedName": "FintechSDKNetworkInterfaces",
        "declKind": "Import",
        "moduleName": "FintechSDKRedirectScenario"
      },
      {
        "kind": "Import",
        "name": "Foundation",
        "printedName": "Foundation",
        "declKind": "Import",
        "moduleName": "FintechSDKRedirectScenario"
      },
      {
        "kind": "Import",
        "name": "FintechSDKNetworkInterfaces",
        "printedName": "FintechSDKNetworkInterfaces",
        "declKind": "Import",
        "moduleName": "FintechSDKRedirectScenario"
      },
      {
        "kind": "Import",
        "name": "Foundation",
        "printedName": "Foundation",
        "declKind": "Import",
        "moduleName": "FintechSDKRedirectScenario"
      },
      {
        "kind": "Import",
        "name": "FintechSDKNetworkInterfaces",
        "printedName": "FintechSDKNetworkInterfaces",
        "declKind": "Import",
        "moduleName": "FintechSDKRedirectScenario"
      },
      {
        "kind": "Import",
        "name": "Foundation",
        "printedName": "Foundation",
        "declKind": "Import",
        "moduleName": "FintechSDKRedirectScenario"
      },
      {
        "kind": "Import",
        "name": "FintechSDKAnalyticsInterfaces",
        "printedName": "FintechSDKAnalyticsInterfaces",
        "declKind": "Import",
        "moduleName": "FintechSDKRedirectScenario"
      },
      {
        "kind": "Import",
        "name": "Foundation",
        "printedName": "Foundation",
        "declKind": "Import",
        "moduleName": "FintechSDKRedirectScenario"
      },
      {
        "kind": "Import",
        "name": "FintechSDKNetworkInterfaces",
        "printedName": "FintechSDKNetworkInterfaces",
        "declKind": "Import",
        "moduleName": "FintechSDKRedirectScenario"
      },
      {
        "kind": "Import",
        "name": "Foundation",
        "printedName": "Foundation",
        "declKind": "Import",
        "moduleName": "FintechSDKRedirectScenario"
      },
      {
        "kind": "Import",
        "name": "FintechSDKAnalyticsInterfaces",
        "printedName": "FintechSDKAnalyticsInterfaces",
        "declKind": "Import",
        "moduleName": "FintechSDKRedirectScenario"
      },
      {
        "kind": "Import",
        "name": "Foundation",
        "printedName": "Foundation",
        "declKind": "Import",
        "moduleName": "FintechSDKRedirectScenario"
      },
      {
        "kind": "Import",
        "name": "FintechSDKNetworkInterfaces",
        "printedName": "FintechSDKNetworkInterfaces",
        "declKind": "Import",
        "moduleName": "FintechSDKRedirectScenario"
      },
      {
        "kind": "Import",
        "name": "Foundation",
        "printedName": "Foundation",
        "declKind": "Import",
        "moduleName": "FintechSDKRedirectScenario"
      },
      {
        "kind": "Import",
        "name": "FintechSDKLoaderScreen",
        "printedName": "FintechSDKLoaderScreen",
        "declKind": "Import",
        "moduleName": "FintechSDKRedirectScenario",
        "declAttributes": [
          "SPIAccessControl"
        ]
      },
      {
        "kind": "Import",
        "name": "FintechSDKCoreUI",
        "printedName": "FintechSDKCoreUI",
        "declKind": "Import",
        "moduleName": "FintechSDKRedirectScenario",
        "declAttributes": [
          "SPIAccessControl"
        ]
      },
      {
        "kind": "Import",
        "name": "FintechSDKAnalyticsInterfaces",
        "printedName": "FintechSDKAnalyticsInterfaces",
        "declKind": "Import",
        "moduleName": "FintechSDKRedirectScenario"
      },
      {
        "kind": "Import",
        "name": "FintechSDKNetworkInterfaces",
        "printedName": "FintechSDKNetworkInterfaces",
        "declKind": "Import",
        "moduleName": "FintechSDKRedirectScenario"
      },
      {
        "kind": "Import",
        "name": "Foundation",
        "printedName": "Foundation",
        "declKind": "Import",
        "moduleName": "FintechSDKRedirectScenario"
      },
      {
        "kind": "Import",
        "name": "UIKit",
        "printedName": "UIKit",
        "declKind": "Import",
        "moduleName": "FintechSDKRedirectScenario"
      },
      {
        "kind": "Import",
        "name": "SwiftUI",
        "printedName": "SwiftUI",
        "declKind": "Import",
        "moduleName": "FintechSDKRedirectScenario"
      },
      {
        "kind": "Import",
        "name": "FintechSDKLoaderScreen",
        "printedName": "FintechSDKLoaderScreen",
        "declKind": "Import",
        "moduleName": "FintechSDKRedirectScenario",
        "declAttributes": [
          "SPIAccessControl"
        ]
      },
      {
        "kind": "TypeDecl",
        "name": "FTRedirectScenario",
        "printedName": "FTRedirectScenario",
        "children": [
          {
            "kind": "Function",
            "name": "run",
            "printedName": "run(paymentURL:)",
            "children": [
              {
                "kind": "TypeNominal",
                "name": "Bool",
                "printedName": "Swift.Bool",
                "usr": "s:Sb"
              },
              {
                "kind": "TypeNominal",
                "name": "URL",
                "printedName": "Foundation.URL",
                "usr": "s:10Foundation3URLV"
              }
            ],
            "declKind": "Func",
            "usr": "s:26FintechSDKRedirectScenario010FTRedirectC0P3run10paymentURLSb10Foundation0G0V_tYaF",
            "mangledName": "$s26FintechSDKRedirectScenario010FTRedirectC0P3run10paymentURLSb10Foundation0G0V_tYaF",
            "moduleName": "FintechSDKRedirectScenario",
            "genericSig": "<τ_0_0 where τ_0_0 : FintechSDKRedirectScenario.FTRedirectScenario>",
            "sugared_genericSig": "<Self where Self : FintechSDKRedirectScenario.FTRedirectScenario>",
            "protocolReq": true,
            "declAttributes": [
              "Custom",
              "DiscardableResult"
            ],
            "reqNewWitnessTableEntry": true,
            "funcSelfKind": "NonMutating"
          }
        ],
        "declKind": "Protocol",
        "usr": "s:26FintechSDKRedirectScenario010FTRedirectC0P",
        "mangledName": "$s26FintechSDKRedirectScenario010FTRedirectC0P",
        "moduleName": "FintechSDKRedirectScenario",
        "declAttributes": [
          "AccessControl"
        ],
        "conformances": [
          {
            "kind": "Conformance",
            "name": "Escapable",
            "printedName": "Escapable",
            "usr": "s:s9EscapableP",
            "mangledName": "$ss9EscapableP"
          },
          {
            "kind": "Conformance",
            "name": "Copyable",
            "printedName": "Copyable",
            "usr": "s:s8CopyableP",
            "mangledName": "$ss8CopyableP"
          }
        ]
      },
      {
        "kind": "TypeDecl",
        "name": "FTRedirectScenarioImpl",
        "printedName": "FTRedirectScenarioImpl",
        "children": [
          {
            "kind": "Constructor",
            "name": "init",
            "printedName": "init(frontbackendNetworkClient:eventReporter:errorReporter:)",
            "children": [
              {
                "kind": "TypeNominal",
                "name": "FTRedirectScenarioImpl",
                "printedName": "FintechSDKRedirectScenario.FTRedirectScenarioImpl",
                "usr": "s:26FintechSDKRedirectScenario010FTRedirectC4ImplC"
              },
              {
                "kind": "TypeNominal",
                "name": "FintechNetworkClient",
                "printedName": "any FintechSDKNetworkInterfaces.FintechNetworkClient",
                "usr": "s:27FintechSDKNetworkInterfaces0A13NetworkClientP"
              },
              {
                "kind": "TypeNominal",
                "name": "FintechAnalyticsEventReporter",
                "printedName": "any FintechSDKAnalyticsInterfaces.FintechAnalyticsEventReporter",
                "usr": "s:29FintechSDKAnalyticsInterfaces0A22AnalyticsEventReporterP"
              },
              {
                "kind": "TypeNominal",
                "name": "FintechAnalyticsErrorReporter",
                "printedName": "any FintechSDKAnalyticsInterfaces.FintechAnalyticsErrorReporter",
                "usr": "s:29FintechSDKAnalyticsInterfaces0A22AnalyticsErrorReporterP"
              }
            ],
            "declKind": "Constructor",
            "usr": "s:26FintechSDKRedirectScenario010FTRedirectC4ImplC25frontbackendNetworkClient13eventReporter05errorJ0AC0A20SDKNetworkInterfaces0agH0_p_0a12SDKAnalyticsM00a14AnalyticsEventJ0_pAI0ao5ErrorJ0_ptcfc",
            "mangledName": "$s26FintechSDKRedirectScenario010FTRedirectC4ImplC25frontbackendNetworkClient13eventReporter05errorJ0AC0A20SDKNetworkInterfaces0agH0_p_0a12SDKAnalyticsM00a14AnalyticsEventJ0_pAI0ao5ErrorJ0_ptcfc",
            "moduleName": "FintechSDKRedirectScenario",
            "declAttributes": [
              "AccessControl"
            ],
            "init_kind": "Designated"
          },
          {
            "kind": "Function",
            "name": "run",
            "printedName": "run(paymentURL:)",
            "children": [
              {
                "kind": "TypeNominal",
                "name": "Bool",
                "printedName": "Swift.Bool",
                "usr": "s:Sb"
              },
              {
                "kind": "TypeNominal",
                "name": "URL",
                "printedName": "Foundation.URL",
                "usr": "s:10Foundation3URLV"
              }
            ],
            "declKind": "Func",
            "usr": "s:26FintechSDKRedirectScenario010FTRedirectC4ImplC3run10paymentURLSb10Foundation0H0V_tYaF",
            "mangledName": "$s26FintechSDKRedirectScenario010FTRedirectC4ImplC3run10paymentURLSb10Foundation0H0V_tYaF",
            "moduleName": "FintechSDKRedirectScenario",
            "declAttributes": [
              "Final",
              "AccessControl",
              "Custom"
            ],
            "funcSelfKind": "NonMutating"
          },
          {
            "kind": "Function",
            "name": "runLogic",
            "printedName": "runLogic(with:)",
            "children": [
              {
                "kind": "TypeNominal",
                "name": "Bool",
                "printedName": "Swift.Bool",
                "usr": "s:Sb"
              },
              {
                "kind": "TypeNominal",
                "name": "URL",
                "printedName": "Foundation.URL",
                "usr": "s:10Foundation3URLV"
              }
            ],
            "declKind": "Func",
            "usr": "s:26FintechSDKRedirectScenario010FTRedirectC4ImplC8runLogic4withSb10Foundation3URLV_tYaF",
            "mangledName": "$s26FintechSDKRedirectScenario010FTRedirectC4ImplC8runLogic4withSb10Foundation3URLV_tYaF",
            "moduleName": "FintechSDKRedirectScenario",
            "declAttributes": [
              "Final",
              "AccessControl"
            ],
            "funcSelfKind": "NonMutating"
          }
        ],
        "declKind": "Class",
        "usr": "s:26FintechSDKRedirectScenario010FTRedirectC4ImplC",
        "mangledName": "$s26FintechSDKRedirectScenario010FTRedirectC4ImplC",
        "moduleName": "FintechSDKRedirectScenario",
        "declAttributes": [
          "Final",
          "AccessControl"
        ],
        "conformances": [
          {
            "kind": "Conformance",
            "name": "Copyable",
            "printedName": "Copyable",
            "usr": "s:s8CopyableP",
            "mangledName": "$ss8CopyableP"
          },
          {
            "kind": "Conformance",
            "name": "Escapable",
            "printedName": "Escapable",
            "usr": "s:s9EscapableP",
            "mangledName": "$ss9EscapableP"
          },
          {
            "kind": "Conformance",
            "name": "FTRedirectScenario",
            "printedName": "FTRedirectScenario",
            "usr": "s:26FintechSDKRedirectScenario010FTRedirectC0P",
            "mangledName": "$s26FintechSDKRedirectScenario010FTRedirectC0P"
          }
        ]
      },
      {
        "kind": "Import",
        "name": "Foundation",
        "printedName": "Foundation",
        "declKind": "Import",
        "moduleName": "FintechSDKRedirectScenario"
      },
      {
        "kind": "Import",
        "name": "FintechSDKNetworkInterfaces",
        "printedName": "FintechSDKNetworkInterfaces",
        "declKind": "Import",
        "moduleName": "FintechSDKRedirectScenario"
      },
      {
        "kind": "Import",
        "name": "Foundation",
        "printedName": "Foundation",
        "declKind": "Import",
        "moduleName": "FintechSDKRedirectScenario"
      },
      {
        "kind": "Import",
        "name": "FintechSDKNetworkInterfaces",
        "printedName": "FintechSDKNetworkInterfaces",
        "declKind": "Import",
        "moduleName": "FintechSDKRedirectScenario"
      },
      {
        "kind": "Import",
        "name": "Foundation",
        "printedName": "Foundation",
        "declKind": "Import",
        "moduleName": "FintechSDKRedirectScenario"
      },
      {
        "kind": "Import",
        "name": "FintechSDKNetworkInterfaces",
        "printedName": "FintechSDKNetworkInterfaces",
        "declKind": "Import",
        "moduleName": "FintechSDKRedirectScenario"
      },
      {
        "kind": "Import",
        "name": "FintechSDKAnalyticsInterfaces",
        "printedName": "FintechSDKAnalyticsInterfaces",
        "declKind": "Import",
        "moduleName": "FintechSDKRedirectScenario"
      },
      {
        "kind": "Import",
        "name": "Foundation",
        "printedName": "Foundation",
        "declKind": "Import",
        "moduleName": "FintechSDKRedirectScenario"
      },
      {
        "kind": "Import",
        "name": "FintechSDKNetworkInterfaces",
        "printedName": "FintechSDKNetworkInterfaces",
        "declKind": "Import",
        "moduleName": "FintechSDKRedirectScenario"
      },
      {
        "kind": "Import",
        "name": "Foundation",
        "printedName": "Foundation",
        "declKind": "Import",
        "moduleName": "FintechSDKRedirectScenario"
      },
      {
        "kind": "Import",
        "name": "FintechSDKAnalyticsInterfaces",
        "printedName": "FintechSDKAnalyticsInterfaces",
        "declKind": "Import",
        "moduleName": "FintechSDKRedirectScenario"
      },
      {
        "kind": "Import",
        "name": "Foundation",
        "printedName": "Foundation",
        "declKind": "Import",
        "moduleName": "FintechSDKRedirectScenario"
      },
      {
        "kind": "Import",
        "name": "FintechSDKNetworkInterfaces",
        "printedName": "FintechSDKNetworkInterfaces",
        "declKind": "Import",
        "moduleName": "FintechSDKRedirectScenario"
      },
      {
        "kind": "Import",
        "name": "Foundation",
        "printedName": "Foundation",
        "declKind": "Import",
        "moduleName": "FintechSDKRedirectScenario"
      },
      {
        "kind": "Import",
        "name": "Foundation",
        "printedName": "Foundation",
        "declKind": "Import",
        "moduleName": "FintechSDKRedirectScenario"
      },
      {
        "kind": "Import",
        "name": "Foundation",
        "printedName": "Foundation",
        "declKind": "Import",
        "moduleName": "FintechSDKRedirectScenario"
      },
      {
        "kind": "Import",
        "name": "Foundation",
        "printedName": "Foundation",
        "declKind": "Import",
        "moduleName": "FintechSDKRedirectScenario"
      },
      {
        "kind": "Import",
        "name": "Foundation",
        "printedName": "Foundation",
        "declKind": "Import",
        "moduleName": "FintechSDKRedirectScenario"
      },
      {
        "kind": "TypeDecl",
        "name": "Array",
        "printedName": "Array",
        "declKind": "Struct",
        "usr": "s:Sa",
        "mangledName": "$sSa",
        "moduleName": "Swift",
        "genericSig": "<τ_0_0>",
        "sugared_genericSig": "<Element>",
        "declAttributes": [
          "EagerMove",
          "Frozen"
        ],
        "isExternal": true,
        "conformances": [
          {
            "kind": "Conformance",
            "name": "_DestructorSafeContainer",
            "printedName": "_DestructorSafeContainer",
            "usr": "s:s24_DestructorSafeContainerP",
            "mangledName": "$ss24_DestructorSafeContainerP"
          },
          {
            "kind": "Conformance",
            "name": "Copyable",
            "printedName": "Copyable",
            "usr": "s:s8CopyableP",
            "mangledName": "$ss8CopyableP"
          },
          {
            "kind": "Conformance",
            "name": "Escapable",
            "printedName": "Escapable",
            "usr": "s:s9EscapableP",
            "mangledName": "$ss9EscapableP"
          },
          {
            "kind": "Conformance",
            "name": "Equatable",
            "printedName": "Equatable",
            "usr": "s:SQ",
            "mangledName": "$sSQ"
          },
          {
            "kind": "Conformance",
            "name": "_ArrayProtocol",
            "printedName": "_ArrayProtocol",
            "children": [
              {
                "kind": "TypeWitness",
                "name": "_Buffer",
                "printedName": "_Buffer",
                "children": [
                  {
                    "kind": "TypeNominal",
                    "name": "_ArrayBuffer",
                    "printedName": "Swift._ArrayBuffer<τ_0_0>",
                    "children": [
                      {
                        "kind": "TypeNominal",
                        "name": "GenericTypeParam",
                        "printedName": "τ_0_0"
                      }
                    ],
                    "usr": "s:s12_ArrayBufferV"
                  }
                ]
              }
            ],
            "usr": "s:s14_ArrayProtocolP",
            "mangledName": "$ss14_ArrayProtocolP"
          },
          {
            "kind": "Conformance",
            "name": "RandomAccessCollection",
            "printedName": "RandomAccessCollection",
            "children": [
              {
                "kind": "TypeWitness",
                "name": "Element",
                "printedName": "Element",
                "children": [
                  {
                    "kind": "TypeNominal",
                    "name": "GenericTypeParam",
                    "printedName": "τ_0_0"
                  }
                ]
              },
              {
                "kind": "TypeWitness",
                "name": "Index",
                "printedName": "Index",
                "children": [
                  {
                    "kind": "TypeNominal",
                    "name": "Int",
                    "printedName": "Swift.Int",
                    "usr": "s:Si"
                  }
                ]
              },
              {
                "kind": "TypeWitness",
                "name": "SubSequence",
                "printedName": "SubSequence",
                "children": [
                  {
                    "kind": "TypeNominal",
                    "name": "ArraySlice",
                    "printedName": "Swift.ArraySlice<τ_0_0>",
                    "children": [
                      {
                        "kind": "TypeNominal",
                        "name": "GenericTypeParam",
                        "printedName": "τ_0_0"
                      }
                    ],
                    "usr": "s:s10ArraySliceV"
                  }
                ]
              },
              {
                "kind": "TypeWitness",
                "name": "Indices",
                "printedName": "Indices",
                "children": [
                  {
                    "kind": "TypeNominal",
                    "name": "Range",
                    "printedName": "Swift.Range<Swift.Int>",
                    "children": [
                      {
                        "kind": "TypeNominal",
                        "name": "Int",
                        "printedName": "Swift.Int",
                        "usr": "s:Si"
                      }
                    ],
                    "usr": "s:Sn"
                  }
                ]
              }
            ],
            "usr": "s:Sk",
            "mangledName": "$sSk"
          },
          {
            "kind": "Conformance",
            "name": "MutableCollection",
            "printedName": "MutableCollection",
            "children": [
              {
                "kind": "TypeWitness",
                "name": "Element",
                "printedName": "Element",
                "children": [
                  {
                    "kind": "TypeNominal",
                    "name": "GenericTypeParam",
                    "printedName": "τ_0_0"
                  }
                ]
              },
              {
                "kind": "TypeWitness",
                "name": "Index",
                "printedName": "Index",
                "children": [
                  {
                    "kind": "TypeNominal",
                    "name": "Int",
                    "printedName": "Swift.Int",
                    "usr": "s:Si"
                  }
                ]
              },
              {
                "kind": "TypeWitness",
                "name": "SubSequence",
                "printedName": "SubSequence",
                "children": [
                  {
                    "kind": "TypeNominal",
                    "name": "ArraySlice",
                    "printedName": "Swift.ArraySlice<τ_0_0>",
                    "children": [
                      {
                        "kind": "TypeNominal",
                        "name": "GenericTypeParam",
                        "printedName": "τ_0_0"
                      }
                    ],
                    "usr": "s:s10ArraySliceV"
                  }
                ]
              }
            ],
            "usr": "s:SM",
            "mangledName": "$sSM"
          },
          {
            "kind": "Conformance",
            "name": "BidirectionalCollection",
            "printedName": "BidirectionalCollection",
            "children": [
              {
                "kind": "TypeWitness",
                "name": "Element",
                "printedName": "Element",
                "children": [
                  {
                    "kind": "TypeNominal",
                    "name": "GenericTypeParam",
                    "printedName": "τ_0_0"
                  }
                ]
              },
              {
                "kind": "TypeWitness",
                "name": "Index",
                "printedName": "Index",
                "children": [
                  {
                    "kind": "TypeNominal",
                    "name": "Int",
                    "printedName": "Swift.Int",
                    "usr": "s:Si"
                  }
                ]
              },
              {
                "kind": "TypeWitness",
                "name": "SubSequence",
                "printedName": "SubSequence",
                "children": [
                  {
                    "kind": "TypeNominal",
                    "name": "ArraySlice",
                    "printedName": "Swift.ArraySlice<τ_0_0>",
                    "children": [
                      {
                        "kind": "TypeNominal",
                        "name": "GenericTypeParam",
                        "printedName": "τ_0_0"
                      }
                    ],
                    "usr": "s:s10ArraySliceV"
                  }
                ]
              },
              {
                "kind": "TypeWitness",
                "name": "Indices",
                "printedName": "Indices",
                "children": [
                  {
                    "kind": "TypeNominal",
                    "name": "Range",
                    "printedName": "Swift.Range<Swift.Int>",
                    "children": [
                      {
                        "kind": "TypeNominal",
                        "name": "Int",
                        "printedName": "Swift.Int",
                        "usr": "s:Si"
                      }
                    ],
                    "usr": "s:Sn"
                  }
                ]
              }
            ],
            "usr": "s:SK",
            "mangledName": "$sSK"
          },
          {
            "kind": "Conformance",
            "name": "Collection",
            "printedName": "Collection",
            "children": [
              {
                "kind": "TypeWitness",
                "name": "Element",
                "printedName": "Element",
                "children": [
                  {
                    "kind": "TypeNominal",
                    "name": "GenericTypeParam",
                    "printedName": "τ_0_0"
                  }
                ]
              },
              {
                "kind": "TypeWitness",
                "name": "Index",
                "printedName": "Index",
                "children": [
                  {
                    "kind": "TypeNominal",
                    "name": "Int",
                    "printedName": "Swift.Int",
                    "usr": "s:Si"
                  }
                ]
              },
              {
                "kind": "TypeWitness",
                "name": "Iterator",
                "printedName": "Iterator",
                "children": [
                  {
                    "kind": "TypeNominal",
                    "name": "IndexingIterator",
                    "printedName": "Swift.IndexingIterator<[τ_0_0]>",
                    "children": [
                      {
                        "kind": "TypeNominal",
                        "name": "Array",
                        "printedName": "[τ_0_0]",
                        "children": [
                          {
                            "kind": "TypeNominal",
                            "name": "GenericTypeParam",
                            "printedName": "τ_0_0"
                          }
                        ],
                        "usr": "s:Sa"
                      }
                    ],
                    "usr": "s:s16IndexingIteratorV"
                  }
                ]
              },
              {
                "kind": "TypeWitness",
                "name": "SubSequence",
                "printedName": "SubSequence",
                "children": [
                  {
                    "kind": "TypeNominal",
                    "name": "ArraySlice",
                    "printedName": "Swift.ArraySlice<τ_0_0>",
                    "children": [
                      {
                        "kind": "TypeNominal",
                        "name": "GenericTypeParam",
                        "printedName": "τ_0_0"
                      }
                    ],
                    "usr": "s:s10ArraySliceV"
                  }
                ]
              },
              {
                "kind": "TypeWitness",
                "name": "Indices",
                "printedName": "Indices",
                "children": [
                  {
                    "kind": "TypeNominal",
                    "name": "Range",
                    "printedName": "Swift.Range<Swift.Int>",
                    "children": [
                      {
                        "kind": "TypeNominal",
                        "name": "Int",
                        "printedName": "Swift.Int",
                        "usr": "s:Si"
                      }
                    ],
                    "usr": "s:Sn"
                  }
                ]
              }
            ],
            "usr": "s:Sl",
            "mangledName": "$sSl"
          },
          {
            "kind": "Conformance",
            "name": "Sequence",
            "printedName": "Sequence",
            "children": [
              {
                "kind": "TypeWitness",
                "name": "Element",
                "printedName": "Element",
                "children": [
                  {
                    "kind": "TypeNominal",
                    "name": "GenericTypeParam",
                    "printedName": "τ_0_0"
                  }
                ]
              },
              {
                "kind": "TypeWitness",
                "name": "Iterator",
                "printedName": "Iterator",
                "children": [
                  {
                    "kind": "TypeNominal",
                    "name": "IndexingIterator",
                    "printedName": "Swift.IndexingIterator<[τ_0_0]>",
                    "children": [
                      {
                        "kind": "TypeNominal",
                        "name": "Array",
                        "printedName": "[τ_0_0]",
                        "children": [
                          {
                            "kind": "TypeNominal",
                            "name": "GenericTypeParam",
                            "printedName": "τ_0_0"
                          }
                        ],
                        "usr": "s:Sa"
                      }
                    ],
                    "usr": "s:s16IndexingIteratorV"
                  }
                ]
              }
            ],
            "usr": "s:ST",
            "mangledName": "$sST"
          },
          {
            "kind": "Conformance",
            "name": "ExpressibleByArrayLiteral",
            "printedName": "ExpressibleByArrayLiteral",
            "children": [
              {
                "kind": "TypeWitness",
                "name": "ArrayLiteralElement",
                "printedName": "ArrayLiteralElement",
                "children": [
                  {
                    "kind": "TypeNominal",
                    "name": "GenericTypeParam",
                    "printedName": "τ_0_0"
                  }
                ]
              }
            ],
            "usr": "s:s25ExpressibleByArrayLiteralP",
            "mangledName": "$ss25ExpressibleByArrayLiteralP"
          },
          {
            "kind": "Conformance",
            "name": "RangeReplaceableCollection",
            "printedName": "RangeReplaceableCollection",
            "children": [
              {
                "kind": "TypeWitness",
                "name": "SubSequence",
                "printedName": "SubSequence",
                "children": [
                  {
                    "kind": "TypeNominal",
                    "name": "ArraySlice",
                    "printedName": "Swift.ArraySlice<τ_0_0>",
                    "children": [
                      {
                        "kind": "TypeNominal",
                        "name": "GenericTypeParam",
                        "printedName": "τ_0_0"
                      }
                    ],
                    "usr": "s:s10ArraySliceV"
                  }
                ]
              }
            ],
            "usr": "s:Sm",
            "mangledName": "$sSm"
          },
          {
            "kind": "Conformance",
            "name": "CustomReflectable",
            "printedName": "CustomReflectable",
            "usr": "s:s17CustomReflectableP",
            "mangledName": "$ss17CustomReflectableP"
          },
          {
            "kind": "Conformance",
            "name": "CustomStringConvertible",
            "printedName": "CustomStringConvertible",
            "usr": "s:s23CustomStringConvertibleP",
            "mangledName": "$ss23CustomStringConvertibleP"
          },
          {
            "kind": "Conformance",
            "name": "CustomDebugStringConvertible",
            "printedName": "CustomDebugStringConvertible",
            "usr": "s:s28CustomDebugStringConvertibleP",
            "mangledName": "$ss28CustomDebugStringConvertibleP"
          },
          {
            "kind": "Conformance",
            "name": "Hashable",
            "printedName": "Hashable",
            "usr": "s:SH",
            "mangledName": "$sSH"
          },
          {
            "kind": "Conformance",
            "name": "_HasCustomAnyHashableRepresentation",
            "printedName": "_HasCustomAnyHashableRepresentation",
            "usr": "s:s35_HasCustomAnyHashableRepresentationP",
            "mangledName": "$ss35_HasCustomAnyHashableRepresentationP"
          },
          {
            "kind": "Conformance",
            "name": "Sendable",
            "printedName": "Sendable",
            "usr": "s:s8SendableP",
            "mangledName": "$ss8SendableP"
          },
          {
            "kind": "Conformance",
            "name": "Encodable",
            "printedName": "Encodable",
            "usr": "s:SE",
            "mangledName": "$sSE"
          },
          {
            "kind": "Conformance",
            "name": "Decodable",
            "printedName": "Decodable",
            "usr": "s:Se",
            "mangledName": "$sSe"
          },
          {
            "kind": "Conformance",
            "name": "_HasContiguousBytes",
            "printedName": "_HasContiguousBytes",
            "usr": "s:s19_HasContiguousBytesP",
            "mangledName": "$ss19_HasContiguousBytesP"
          },
          {
            "kind": "Conformance",
            "name": "_ObjectiveCBridgeable",
            "printedName": "_ObjectiveCBridgeable",
            "children": [
              {
                "kind": "TypeWitness",
                "name": "_ObjectiveCType",
                "printedName": "_ObjectiveCType",
                "children": [
                  {
                    "kind": "TypeNominal",
                    "name": "NSArray",
                    "printedName": "Foundation.NSArray",
                    "usr": "c:objc(cs)NSArray"
                  }
                ]
              }
            ],
            "usr": "s:s21_ObjectiveCBridgeableP",
            "mangledName": "$ss21_ObjectiveCBridgeableP"
          },
          {
            "kind": "Conformance",
            "name": "CVarArg",
            "printedName": "CVarArg",
            "usr": "s:s7CVarArgP",
            "mangledName": "$ss7CVarArgP"
          },
          {
            "kind": "Conformance",
            "name": "DataProtocol",
            "printedName": "DataProtocol",
            "children": [
              {
                "kind": "TypeWitness",
                "name": "Regions",
                "printedName": "Regions",
                "children": [
                  {
                    "kind": "TypeNominal",
                    "name": "CollectionOfOne",
                    "printedName": "Swift.CollectionOfOne<[Swift.UInt8]>",
                    "children": [
                      {
                        "kind": "TypeNominal",
                        "name": "Array",
                        "printedName": "[Swift.UInt8]",
                        "children": [
                          {
                            "kind": "TypeNominal",
                            "name": "UInt8",
                            "printedName": "Swift.UInt8",
                            "usr": "s:s5UInt8V"
                          }
                        ],
                        "usr": "s:Sa"
                      }
                    ],
                    "usr": "s:s15CollectionOfOneV"
                  }
                ]
              }
            ],
            "usr": "s:10Foundation12DataProtocolP",
            "mangledName": "$s10Foundation12DataProtocolP"
          },
          {
            "kind": "Conformance",
            "name": "MutableDataProtocol",
            "printedName": "MutableDataProtocol",
            "usr": "s:10Foundation19MutableDataProtocolP",
            "mangledName": "$s10Foundation19MutableDataProtocolP"
          },
          {
            "kind": "Conformance",
            "name": "ContiguousBytes",
            "printedName": "ContiguousBytes",
            "usr": "s:10Foundation15ContiguousBytesP",
            "mangledName": "$s10Foundation15ContiguousBytesP"
          },
          {
            "kind": "Conformance",
            "name": "EncodableWithConfiguration",
            "printedName": "EncodableWithConfiguration",
            "children": [
              {
                "kind": "TypeWitness",
                "name": "EncodingConfiguration",
                "printedName": "EncodingConfiguration",
                "children": [
                  {
                    "kind": "TypeNominal",
                    "name": "DependentMember",
                    "printedName": "τ_0_0.EncodingConfiguration"
                  }
                ]
              }
            ],
            "usr": "s:10Foundation26EncodableWithConfigurationP",
            "mangledName": "$s10Foundation26EncodableWithConfigurationP"
          },
          {
            "kind": "Conformance",
            "name": "DecodableWithConfiguration",
            "printedName": "DecodableWithConfiguration",
            "children": [
              {
                "kind": "TypeWitness",
                "name": "DecodingConfiguration",
                "printedName": "DecodingConfiguration",
                "children": [
                  {
                    "kind": "TypeNominal",
                    "name": "DependentMember",
                    "printedName": "τ_0_0.DecodingConfiguration"
                  }
                ]
              }
            ],
            "usr": "s:10Foundation26DecodableWithConfigurationP",
            "mangledName": "$s10Foundation26DecodableWithConfigurationP"
          }
        ]
      }
    ],
    "json_format_version": 8
  },
  "ConstValues": [
    {
      "filePath": "\/usr\/local\/place\/sandbox-data\/tasks\/4\/0\/4000356504\/arcadia\/mobile\/fintech-sdk\/ios\/FintechSDK\/Scenarios\/Redirect\/Polling\/FTPollingOrderScenario.swift",
      "kind": "IntegerLiteral",
      "offset": 5213,
      "length": 1,
      "value": "1"
    },
    {
      "filePath": "\/usr\/local\/place\/sandbox-data\/tasks\/4\/0\/4000356504\/arcadia\/mobile\/fintech-sdk\/ios\/FintechSDK\/Scenarios\/Redirect\/Polling\/FTPollingOrderScenario.swift",
      "kind": "IntegerLiteral",
      "offset": 5244,
      "length": 2,
      "value": "30"
    },
    {
      "filePath": "\/usr\/local\/place\/sandbox-data\/tasks\/4\/0\/4000356504\/arcadia\/mobile\/fintech-sdk\/ios\/FintechSDK\/Scenarios\/Redirect\/Polling\/FTPollingOrderScenario.swift",
      "kind": "IntegerLiteral",
      "offset": 5249,
      "length": 2,
      "value": "60"
    },
    {
      "filePath": "\/usr\/local\/place\/sandbox-data\/tasks\/4\/0\/4000356504\/arcadia\/mobile\/fintech-sdk\/ios\/FintechSDK\/Scenarios\/Redirect\/Polling\/Network\/FTOrderMetaEndpoint.swift",
      "kind": "StringLiteral",
      "offset": 323,
      "length": 36,
      "value": "\"\/api\/v1\/orders\/meta\/by-payment-url\""
    },
    {
      "filePath": "\/usr\/local\/place\/sandbox-data\/tasks\/4\/0\/4000356504\/arcadia\/mobile\/fintech-sdk\/ios\/FintechSDK\/Scenarios\/Redirect\/Polling\/Network\/FTOrderMetaEndpoint.swift",
      "kind": "IntegerLiteral",
      "offset": 399,
      "length": 2,
      "value": "10"
    },
    {
      "filePath": "\/usr\/local\/place\/sandbox-data\/tasks\/4\/0\/4000356504\/arcadia\/mobile\/fintech-sdk\/ios\/FintechSDK\/Scenarios\/Redirect\/Polling\/Network\/FTOrderMetaEndpoint.swift",
      "kind": "StringLiteral",
      "offset": 885,
      "length": 9,
      "value": "\"PENDING\""
    },
    {
      "filePath": "\/usr\/local\/place\/sandbox-data\/tasks\/4\/0\/4000356504\/arcadia\/mobile\/fintech-sdk\/ios\/FintechSDK\/Scenarios\/Redirect\/Polling\/Network\/FTOrderMetaEndpoint.swift",
      "kind": "StringLiteral",
      "offset": 914,
      "length": 9,
      "value": "\"SUCCESS\""
    },
    {
      "filePath": "\/usr\/local\/place\/sandbox-data\/tasks\/4\/0\/4000356504\/arcadia\/mobile\/fintech-sdk\/ios\/FintechSDK\/Scenarios\/Redirect\/Polling\/Network\/FTOrderMetaEndpoint.swift",
      "kind": "StringLiteral",
      "offset": 942,
      "length": 8,
      "value": "\"FAILED\""
    },
    {
      "filePath": "\/usr\/local\/place\/sandbox-data\/tasks\/4\/0\/4000356504\/arcadia\/mobile\/fintech-sdk\/ios\/FintechSDK\/Scenarios\/Redirect\/Polling\/PaymentResultParser\/PaymentResultParser.swift",
      "kind": "StringLiteral",
      "offset": 1998,
      "length": 9,
      "value": "\"success\""
    },
    {
      "filePath": "\/usr\/local\/place\/sandbox-data\/tasks\/4\/0\/4000356504\/arcadia\/mobile\/fintech-sdk\/ios\/FintechSDK\/Scenarios\/Redirect\/Polling\/PaymentResultParser\/PaymentResultParser.swift",
      "kind": "StringLiteral",
      "offset": 2024,
      "length": 7,
      "value": "\"error\""
    },
    {
      "filePath": "\/usr\/local\/place\/sandbox-data\/tasks\/4\/0\/4000356504\/arcadia\/mobile\/fintech-sdk\/ios\/FintechSDK\/Scenarios\/Redirect\/Polling\/PaymentResultParser\/PaymentResultParser.swift",
      "kind": "StringLiteral",
      "offset": 2050,
      "length": 7,
      "value": "\"abort\""
    },
    {
      "filePath": "\/usr\/local\/place\/sandbox-data\/tasks\/4\/0\/4000356504\/arcadia\/mobile\/fintech-sdk\/ios\/FintechSDK\/Scenarios\/Redirect\/Polling\/PaymentResultParser\/PaymentResultParser.swift",
      "kind": "StringLiteral",
      "offset": 2142,
      "length": 16,
      "value": "\"PAYMENT_FAILED\""
    },
    {
      "filePath": "\/usr\/local\/place\/sandbox-data\/tasks\/4\/0\/4000356504\/arcadia\/mobile\/fintech-sdk\/ios\/FintechSDK\/Scenarios\/Redirect\/Polling\/PaymentResultParser\/PaymentResultParser.swift",
      "kind": "StringLiteral",
      "offset": 2179,
      "length": 11,
      "value": "\"APP_ERROR\""
    },
    {
      "filePath": "\/usr\/local\/place\/sandbox-data\/tasks\/4\/0\/4000356504\/arcadia\/mobile\/fintech-sdk\/ios\/FintechSDK\/Scenarios\/Redirect\/Polling\/PaymentResultParser\/PaymentResultParser.swift",
      "kind": "StringLiteral",
      "offset": 2214,
      "length": 14,
      "value": "\"INVALID_ARGS\""
    },
    {
      "filePath": "\/usr\/local\/place\/sandbox-data\/tasks\/4\/0\/4000356504\/arcadia\/mobile\/fintech-sdk\/ios\/FintechSDK\/Scenarios\/Redirect\/Polling\/PaymentResultParser\/PaymentResultParser.swift",
      "kind": "StringLiteral",
      "offset": 2253,
      "length": 15,
      "value": "\"ORDER_EXPIRED\""
    },
    {
      "filePath": "\/usr\/local\/place\/sandbox-data\/tasks\/4\/0\/4000356504\/arcadia\/mobile\/fintech-sdk\/ios\/FintechSDK\/Scenarios\/Redirect\/Polling\/PaymentResultParser\/PaymentResultParser.swift",
      "kind": "StringLiteral",
      "offset": 2294,
      "length": 17,
      "value": "\"ORDER_NOT_FOUND\""
    },
    {
      "filePath": "\/usr\/local\/place\/sandbox-data\/tasks\/4\/0\/4000356504\/arcadia\/mobile\/fintech-sdk\/ios\/FintechSDK\/Scenarios\/Redirect\/Polling\/PaymentResultParser\/PaymentResultParser.swift",
      "kind": "StringLiteral",
      "offset": 2336,
      "length": 15,
      "value": "\"UNKNOWN_ERROR\""
    },
    {
      "filePath": "\/usr\/local\/place\/sandbox-data\/tasks\/4\/0\/4000356504\/arcadia\/mobile\/fintech-sdk\/ios\/FintechSDK\/Scenarios\/Redirect\/Polling\/PaymentResultParser\/PaymentResultParser.swift",
      "kind": "StringLiteral",
      "offset": 2397,
      "length": 24,
      "value": "\"AUTHENTICATION_PROBLEM\""
    },
    {
      "filePath": "\/usr\/local\/place\/sandbox-data\/tasks\/4\/0\/4000356504\/arcadia\/mobile\/fintech-sdk\/ios\/FintechSDK\/Scenarios\/Redirect\/Polling\/PaymentResultParser\/PaymentResultParser.swift",
      "kind": "StringLiteral",
      "offset": 2449,
      "length": 19,
      "value": "\"WRONG_MERCHANT_ID\""
    },
    {
      "filePath": "\/usr\/local\/place\/sandbox-data\/tasks\/4\/0\/4000356504\/arcadia\/mobile\/fintech-sdk\/ios\/FintechSDK\/Scenarios\/Redirect\/Polling\/PaymentResultParser\/PaymentResultParser.swift",
      "kind": "StringLiteral",
      "offset": 2525,
      "length": 7,
      "value": "\"https\""
    },
    {
      "filePath": "\/usr\/local\/place\/sandbox-data\/tasks\/4\/0\/4000356504\/arcadia\/mobile\/fintech-sdk\/ios\/FintechSDK\/Scenarios\/Redirect\/Polling\/PaymentResultParser\/PaymentResultParser.swift",
      "kind": "StringLiteral",
      "offset": 2559,
      "length": 9,
      "value": "\"orderId\""
    },
    {
      "filePath": "\/usr\/local\/place\/sandbox-data\/tasks\/4\/0\/4000356504\/arcadia\/mobile\/fintech-sdk\/ios\/FintechSDK\/Scenarios\/Redirect\/Polling\/PaymentResultParser\/PaymentResultParser.swift",
      "kind": "StringLiteral",
      "offset": 2598,
      "length": 12,
      "value": "\"merchantId\""
    },
    {
      "filePath": "\/usr\/local\/place\/sandbox-data\/tasks\/4\/0\/4000356504\/arcadia\/mobile\/fintech-sdk\/ios\/FintechSDK\/Scenarios\/Redirect\/Polling\/PaymentResultParser\/PaymentResultParser.swift",
      "kind": "StringLiteral",
      "offset": 2639,
      "length": 11,
      "value": "\"sessionId\""
    },
    {
      "filePath": "\/usr\/local\/place\/sandbox-data\/tasks\/4\/0\/4000356504\/arcadia\/mobile\/fintech-sdk\/ios\/FintechSDK\/Scenarios\/Redirect\/Polling\/PaymentResultParser\/PaymentResultParser.swift",
      "kind": "StringLiteral",
      "offset": 2676,
      "length": 8,
      "value": "\"result\""
    },
    {
      "filePath": "\/usr\/local\/place\/sandbox-data\/tasks\/4\/0\/4000356504\/arcadia\/mobile\/fintech-sdk\/ios\/FintechSDK\/Scenarios\/Redirect\/Polling\/PaymentResultParser\/PaymentResultParser.swift",
      "kind": "StringLiteral",
      "offset": 2710,
      "length": 8,
      "value": "\"reason\""
    },
    {
      "filePath": "\/usr\/local\/place\/sandbox-data\/tasks\/4\/0\/4000356504\/arcadia\/mobile\/fintech-sdk\/ios\/FintechSDK\/Scenarios\/Redirect\/Polling\/PaymentResultParser\/PaymentResultParser.swift",
      "kind": "StringLiteral",
      "offset": 2747,
      "length": 11,
      "value": "\"userToken\""
    },
    {
      "filePath": "\/usr\/local\/place\/sandbox-data\/tasks\/4\/0\/4000356504\/arcadia\/mobile\/fintech-sdk\/ios\/FintechSDK\/Scenarios\/Redirect\/Polling\/PaymentResultParser\/PaymentResultParser.swift",
      "kind": "StringLiteral",
      "offset": 2789,
      "length": 32,
      "value": "\"merchant.applink.pay.yandex.ru\""
    },
    {
      "filePath": "\/usr\/local\/place\/sandbox-data\/tasks\/4\/0\/4000356504\/arcadia\/mobile\/fintech-sdk\/ios\/FintechSDK\/Scenarios\/Redirect\/Polling\/PaymentResultParser\/PaymentResultParser.swift",
      "kind": "StringLiteral",
      "offset": 2849,
      "length": 40,
      "value": "\"merchant.applink.sandbox.pay.yandex.ru\""
    },
    {
      "filePath": "\/usr\/local\/place\/sandbox-data\/tasks\/4\/0\/4000356504\/arcadia\/mobile\/fintech-sdk\/ios\/FintechSDK\/Scenarios\/Redirect\/Polling\/PaymentResultParser\/PaymentResultParser.swift",
      "kind": "StringLiteral",
      "offset": 2917,
      "length": 37,
      "value": "\"merchant.applink.test.pay.yandex.ru\""
    },
    {
      "filePath": "\/usr\/local\/place\/sandbox-data\/tasks\/4\/0\/4000356504\/arcadia\/mobile\/fintech-sdk\/ios\/FintechSDK\/Scenarios\/Redirect\/Redirect\/URLValidator\/FTDomainURLValidator.swift",
      "kind": "BooleanLiteral",
      "offset": 203,
      "length": 5,
      "value": "false"
    }
  ]
}